odoo/addons/l10n_ar_afipws_fe/README.rst
odoo/addons/l10n_ar_afipws_fe/__init__.py
odoo/addons/l10n_ar_afipws_fe/__manifest__.py
odoo/addons/l10n_ar_afipws_fe/afip_tools.py
odoo/addons/l10n_ar_afipws_fe/data/automatic_post_cron.xml
odoo/addons/l10n_ar_afipws_fe/i18n/es_AR.po
odoo/addons/l10n_ar_afipws_fe/i18n/l10n_ar_afipws_fe.pot
odoo/addons/l10n_ar_afipws_fe/models/__init__.py
odoo/addons/l10n_ar_afipws_fe/models/account_journal.py
odoo/addons/l10n_ar_afipws_fe/models/account_journal_ws.py
odoo/addons/l10n_ar_afipws_fe/models/account_move.py
odoo/addons/l10n_ar_afipws_fe/models/account_move_mipyme.py
odoo/addons/l10n_ar_afipws_fe/models/account_move_wsbfe.py
odoo/addons/l10n_ar_afipws_fe/models/account_move_wsfe.py
odoo/addons/l10n_ar_afipws_fe/models/account_move_wsfex.py
odoo/addons/l10n_ar_afipws_fe/models/afipws_connection.py
odoo/addons/l10n_ar_afipws_fe/models/l10n_latam_document_type.py
odoo/addons/l10n_ar_afipws_fe/models/res_company.py
odoo/addons/l10n_ar_afipws_fe/models/res_config_settings.py
odoo/addons/l10n_ar_afipws_fe/readme/CONTRIBUTORS.rst
odoo/addons/l10n_ar_afipws_fe/readme/DESCRIPTION.rst
odoo/addons/l10n_ar_afipws_fe/readme/HISTORY.rst
odoo/addons/l10n_ar_afipws_fe/readme/ROADMAP.rst
odoo/addons/l10n_ar_afipws_fe/static/description/icon.png
odoo/addons/l10n_ar_afipws_fe/static/description/index.html
odoo/addons/l10n_ar_afipws_fe/views/account_journal_view.xml
odoo/addons/l10n_ar_afipws_fe/views/account_move_view.xml
odoo/addons/l10n_ar_afipws_fe/views/res_config_settings.xml
odoo/addons/l10n_ar_afipws_fe/wizard/__init__.py
odoo/addons/l10n_ar_afipws_fe/wizard/account_validate_account_move.py
odoo/addons/l10n_ar_afipws_fe/wizard/account_validate_account_move_view.xml
odoo_addon_l10n_ar_afipws_fe-16.0.1.0.0.4.dist-info/METADATA
odoo_addon_l10n_ar_afipws_fe-16.0.1.0.0.4.dist-info/WHEEL
odoo_addon_l10n_ar_afipws_fe-16.0.1.0.0.4.dist-info/top_level.txt
odoo_addon_l10n_ar_afipws_fe-16.0.1.0.0.4.dist-info/RECORD
